unit_gears/__init__.py
unit_gears/base_models.py
unit_gears/gear_mapping.py
unit_gears/master_gear_mapping.csv
unit_gears/model_library.py
unit_gears/quantities.py
unit_gears/query.py
unit_gears/stages.py
unit_gears/models/Akyol 2012.json
unit_gears/models/Avadi 2014.json
unit_gears/models/Deshpande 2020.json
unit_gears/models/Gabr 2012.json
unit_gears/models/Gilman 2021.json
unit_gears/models/Grimaldo 2019.json
unit_gears/models/Hoffman 2009.json
unit_gears/models/Laissane 2011.json
unit_gears/models/Laso 2017.json
unit_gears/models/Pravin 2016.json
unit_gears/models/Sala 2019.json
unit_gears/models/Soldo 2019.json
unit_gears/models/Thrane 2006.json
unit_gears/models/Watanabe 2016.json
unit_gears/reference/LCI Model.json
unit_gears/reference/quantities.json
unit_gears/tests/__init__.py
unit_gears/tests/test_base_models.py
unit_gears/tests/test_gear_mapper.py
unit_gears/tests/test_library.py
unit_gears-1.0.6.dist-info/LICENSE
unit_gears-1.0.6.dist-info/METADATA
unit_gears-1.0.6.dist-info/WHEEL
unit_gears-1.0.6.dist-info/top_level.txt
unit_gears-1.0.6.dist-info/RECORD
