Metadata-Version: 2.1
Name: unit_gears
Version: 1.0.6
Home-page: https://github.com/bkuczenski/unit_gears
Author: Brandon Kuczenski
Author-email: bkuczenski@ucsb.edu
License: BSD 3-Clause License
License-File: LICENSE
Requires-Dist: stats-arrays >=0.6.4
Requires-Dist: synonym-dict >=0.1.1
Requires-Dist: numpy <2.0
